nmrsim/__init__.py
nmrsim/_classes.py
nmrsim/_descriptors.py
nmrsim/_utils.py
nmrsim/discrete.py
nmrsim/dnmr.py
nmrsim/firstorder.py
nmrsim/math.py
nmrsim/plt.py
nmrsim/qm.py
nmrsim/bin/Lproduct1.npz
nmrsim/bin/Lproduct10.npz
nmrsim/bin/Lproduct11.npz
nmrsim/bin/Lproduct2.npz
nmrsim/bin/Lproduct3.npz
nmrsim/bin/Lproduct4.npz
nmrsim/bin/Lproduct5.npz
nmrsim/bin/Lproduct6.npz
nmrsim/bin/Lproduct7.npz
nmrsim/bin/Lproduct8.npz
nmrsim/bin/Lproduct9.npz
nmrsim/bin/Lz1.npz
nmrsim/bin/Lz10.npz
nmrsim/bin/Lz11.npz
nmrsim/bin/Lz2.npz
nmrsim/bin/Lz3.npz
nmrsim/bin/Lz4.npz
nmrsim/bin/Lz5.npz
nmrsim/bin/Lz6.npz
nmrsim/bin/Lz7.npz
nmrsim/bin/Lz8.npz
nmrsim/bin/Lz9.npz
nmrsim/bin/T1.npz
nmrsim/bin/T10.npz
nmrsim/bin/T11.npz
nmrsim/bin/T2.npz
nmrsim/bin/T3.npz
nmrsim/bin/T4.npz
nmrsim/bin/T5.npz
nmrsim/bin/T6.npz
nmrsim/bin/T7.npz
nmrsim/bin/T8.npz
nmrsim/bin/T9.npz
nmrsim/bin/__init__.py
nmrsim-0.6.0.post1.dist-info/LICENSE
nmrsim-0.6.0.post1.dist-info/METADATA
nmrsim-0.6.0.post1.dist-info/WHEEL
nmrsim-0.6.0.post1.dist-info/top_level.txt
nmrsim-0.6.0.post1.dist-info/RECORD
